check_execution_time_of_program/__init__.py
check_execution_time_of_program/run_time.py
check_execution_time_of_program-2.0.0.dist-info/LICENSE.TXT
check_execution_time_of_program-2.0.0.dist-info/METADATA
check_execution_time_of_program-2.0.0.dist-info/WHEEL
check_execution_time_of_program-2.0.0.dist-info/top_level.txt
check_execution_time_of_program-2.0.0.dist-info/RECORD
